{
    "child_model_execute_cost_by_ms": [
        14.92300033569336,
        8.63599967956543
    ],
    "child_model_run_time": [
        [
            15485821,
            15500744
        ],
        [
            15500825,
            15509461
        ]
    ],
    "execute_cost": 23.55900001525879,
    "finish_time": 15509470,
    "limit_cost_by_ms": 18.88599967956543,
    "model_name": "resnet50",
    "recv_time": 15485676,
    "tag": "335",
    "total_cost_by_ms": 23.79400062561035,
    "wait_cost": 0.2350006103515625
}
