{
    "child_model_execute_cost_by_ms": [
        18.847999572753906,
        17.374000549316406,
        20.149999618530273
    ],
    "child_model_run_time": [
        [
            29410805,
            29429653
        ],
        [
            29462224,
            29479598
        ],
        [
            29479611,
            29499761
        ]
    ],
    "execute_cost": 56.37200164794922,
    "finish_time": 29499765,
    "limit_cost_by_ms": 47.198333740234375,
    "model_name": "vgg19",
    "recv_time": 29410694,
    "tag": "941",
    "total_cost_by_ms": 89.07099914550781,
    "wait_cost": 32.698997497558594
}
