{
    "child_model_execute_cost_by_ms": [
        18.941999435424805,
        19.28499984741211,
        21.19099998474121
    ],
    "child_model_run_time": [
        [
            20671615,
            20690557
        ],
        [
            20714146,
            20733431
        ],
        [
            20733522,
            20754713
        ]
    ],
    "execute_cost": 59.417999267578125,
    "finish_time": 20754718,
    "limit_cost_by_ms": 47.44166564941406,
    "model_name": "vgg19",
    "recv_time": 20652540,
    "tag": "510",
    "total_cost_by_ms": 102.1780014038086,
    "wait_cost": 42.76000213623047
}
