{
    "child_model_execute_cost_by_ms": [
        15.12600040435791,
        8.395999908447266
    ],
    "child_model_run_time": [
        [
            12515381,
            12530507
        ],
        [
            12530600,
            12538996
        ]
    ],
    "execute_cost": 23.52199935913086,
    "finish_time": 12539000,
    "limit_cost_by_ms": 18.882333755493164,
    "model_name": "resnet50",
    "recv_time": 12507034,
    "tag": "184",
    "total_cost_by_ms": 31.965999603271484,
    "wait_cost": 8.444000244140625
}
