{
    "child_model_execute_cost_by_ms": [
        18.375999450683594,
        17.118999481201172,
        20.88800048828125
    ],
    "child_model_run_time": [
        [
            14853327,
            14871703
        ],
        [
            14871791,
            14888910
        ],
        [
            14897463,
            14918351
        ]
    ],
    "execute_cost": 56.382999420166016,
    "finish_time": 14918357,
    "limit_cost_by_ms": 47.24833297729492,
    "model_name": "vgg19",
    "recv_time": 14853164,
    "tag": "272",
    "total_cost_by_ms": 65.19300079345703,
    "wait_cost": 8.810001373291016
}
