{
    "child_model_execute_cost_by_ms": [
        19.28700065612793,
        19.0,
        20.93600082397461
    ],
    "child_model_run_time": [
        [
            18568940,
            18588227
        ],
        [
            18596492,
            18615492
        ],
        [
            18626088,
            18647024
        ]
    ],
    "execute_cost": 59.22300338745117,
    "finish_time": 18647029,
    "limit_cost_by_ms": 47.19033432006836,
    "model_name": "vgg19",
    "recv_time": 18561324,
    "tag": "513",
    "total_cost_by_ms": 85.70500183105469,
    "wait_cost": 26.481998443603516
}
