{
    "child_model_execute_cost_by_ms": [
        17.649999618530273,
        17.395999908447266,
        20.145000457763672
    ],
    "child_model_run_time": [
        [
            24846021,
            24863671
        ],
        [
            24871999,
            24889395
        ],
        [
            24889478,
            24909623
        ]
    ],
    "execute_cost": 55.19099807739258,
    "finish_time": 24909625,
    "limit_cost_by_ms": 47.24766540527344,
    "model_name": "vgg19",
    "recv_time": 24845883,
    "tag": "624",
    "total_cost_by_ms": 63.742000579833984,
    "wait_cost": 8.551002502441406
}
