{
    "child_model_execute_cost_by_ms": [
        18.101999282836914,
        18.261999130249023,
        19.551000595092773
    ],
    "child_model_run_time": [
        [
            24129458,
            24147560
        ],
        [
            24147592,
            24165854
        ],
        [
            24225164,
            24244715
        ]
    ],
    "execute_cost": 55.915000915527344,
    "finish_time": 24244721,
    "limit_cost_by_ms": 44.711334228515625,
    "model_name": "vgg19",
    "recv_time": 23888791,
    "tag": "239",
    "total_cost_by_ms": 355.92999267578125,
    "wait_cost": 300.0149841308594
}
