{
    "child_model_execute_cost_by_ms": [
        18.825000762939453,
        17.23200035095215,
        20.243999481201172
    ],
    "child_model_run_time": [
        [
            17945964,
            17964789
        ],
        [
            17964832,
            17982064
        ],
        [
            17982104,
            18002348
        ]
    ],
    "execute_cost": 56.30099868774414,
    "finish_time": 18002353,
    "limit_cost_by_ms": 47.152000427246094,
    "model_name": "vgg19",
    "recv_time": 17945858,
    "tag": "376",
    "total_cost_by_ms": 56.494998931884766,
    "wait_cost": 0.194000244140625
}
