{
    "child_model_execute_cost_by_ms": [
        15.515000343322754,
        9.395999908447266
    ],
    "child_model_run_time": [
        [
            22726594,
            22742109
        ],
        [
            22742154,
            22751550
        ]
    ],
    "execute_cost": 24.910999298095703,
    "finish_time": 22751555,
    "limit_cost_by_ms": 18.867666244506836,
    "model_name": "resnet50",
    "recv_time": 22701808,
    "tag": "513",
    "total_cost_by_ms": 49.74700164794922,
    "wait_cost": 24.836002349853516
}
