{
    "child_model_execute_cost_by_ms": [
        14.982999801635742,
        8.902000427246094
    ],
    "child_model_run_time": [
        [
            21681269,
            21696252
        ],
        [
            21704851,
            21713753
        ]
    ],
    "execute_cost": 23.885000228881836,
    "finish_time": 21713765,
    "limit_cost_by_ms": 18.881000518798828,
    "model_name": "resnet50",
    "recv_time": 21681162,
    "tag": "572",
    "total_cost_by_ms": 32.60300064086914,
    "wait_cost": 8.718000411987305
}
