{
    "child_model_execute_cost_by_ms": [
        18.51300048828125,
        21.136999130249023,
        19.827999114990234
    ],
    "child_model_run_time": [
        [
            34203613,
            34222126
        ],
        [
            34284088,
            34305225
        ],
        [
            34305320,
            34325148
        ]
    ],
    "execute_cost": 59.47800064086914,
    "finish_time": 34325152,
    "limit_cost_by_ms": 46.40966796875,
    "model_name": "vgg19",
    "recv_time": 34090429,
    "tag": "681",
    "total_cost_by_ms": 234.72300720214844,
    "wait_cost": 175.24501037597656
}
