{
    "child_model_execute_cost_by_ms": [
        19.177000045776367,
        17.722999572753906,
        21.454999923706055
    ],
    "child_model_run_time": [
        [
            31126071,
            31145248
        ],
        [
            31145334,
            31163057
        ],
        [
            31163137,
            31184592
        ]
    ],
    "execute_cost": 58.355003356933594,
    "finish_time": 31184597,
    "limit_cost_by_ms": 47.31133270263672,
    "model_name": "vgg19",
    "recv_time": 31125903,
    "tag": "872",
    "total_cost_by_ms": 58.694000244140625,
    "wait_cost": 0.33899688720703125
}
