{
    "child_model_execute_cost_by_ms": [
        14.76200008392334,
        8.791999816894531
    ],
    "child_model_run_time": [
        [
            23771781,
            23786543
        ],
        [
            23794407,
            23803199
        ]
    ],
    "execute_cost": 23.554000854492188,
    "finish_time": 23803206,
    "limit_cost_by_ms": 18.854000091552734,
    "model_name": "resnet50",
    "recv_time": 23760755,
    "tag": "557",
    "total_cost_by_ms": 42.45100021362305,
    "wait_cost": 18.89699935913086
}
