{
    "child_model_execute_cost_by_ms": [
        20.768999099731445,
        17.066999435424805,
        19.461999893188477
    ],
    "child_model_run_time": [
        [
            39668848,
            39689617
        ],
        [
            39689653,
            39706720
        ],
        [
            39734550,
            39754012
        ]
    ],
    "execute_cost": 57.297996520996094,
    "finish_time": 39754018,
    "limit_cost_by_ms": 42.855777740478516,
    "model_name": "vgg19",
    "recv_time": 39475661,
    "tag": "926",
    "total_cost_by_ms": 278.35699462890625,
    "wait_cost": 221.05899047851563
}
