{
    "child_model_execute_cost_by_ms": [
        13.994000434875488,
        8.718000411987305
    ],
    "child_model_run_time": [
        [
            23167685,
            23181679
        ],
        [
            23181765,
            23190483
        ]
    ],
    "execute_cost": 22.71200180053711,
    "finish_time": 23190489,
    "limit_cost_by_ms": 18.982666015625,
    "model_name": "resnet50",
    "recv_time": 23167572,
    "tag": "572",
    "total_cost_by_ms": 22.91699981689453,
    "wait_cost": 0.20499801635742188
}
