{
    "child_model_execute_cost_by_ms": [
        18.48900032043457,
        17.57900047302246,
        21.80699920654297
    ],
    "child_model_run_time": [
        [
            23668129,
            23686618
        ],
        [
            23686656,
            23704235
        ],
        [
            23717689,
            23739496
        ]
    ],
    "execute_cost": 57.875,
    "finish_time": 23739499,
    "limit_cost_by_ms": 46.47666549682617,
    "model_name": "vgg19",
    "recv_time": 23668064,
    "tag": "234",
    "total_cost_by_ms": 71.43499755859375,
    "wait_cost": 13.55999755859375
}
