{
    "child_model_execute_cost_by_ms": [
        19.038000106811523,
        18.62299919128418,
        19.67099952697754
    ],
    "child_model_run_time": [
        [
            19754812,
            19773850
        ],
        [
            19797716,
            19816339
        ],
        [
            19824072,
            19843743
        ]
    ],
    "execute_cost": 57.332000732421875,
    "finish_time": 19843746,
    "limit_cost_by_ms": 45.62333297729492,
    "model_name": "vgg19",
    "recv_time": 19754615,
    "tag": "488",
    "total_cost_by_ms": 89.13099670410156,
    "wait_cost": 31.798995971679688
}
