{
    "child_model_execute_cost_by_ms": [
        19.010000228881836,
        17.65399932861328,
        20.96299934387207
    ],
    "child_model_run_time": [
        [
            18858620,
            18877630
        ],
        [
            18877717,
            18895371
        ],
        [
            18930267,
            18951230
        ]
    ],
    "execute_cost": 57.62699890136719,
    "finish_time": 18951234,
    "limit_cost_by_ms": 47.207332611083984,
    "model_name": "vgg19",
    "recv_time": 18858560,
    "tag": "482",
    "total_cost_by_ms": 92.67400360107422,
    "wait_cost": 35.04700469970703
}
