{
    "child_model_execute_cost_by_ms": [
        14.27400016784668,
        8.64799976348877
    ],
    "child_model_run_time": [
        [
            27933239,
            27947513
        ],
        [
            27947549,
            27956197
        ]
    ],
    "execute_cost": 22.922000885009766,
    "finish_time": 27956203,
    "limit_cost_by_ms": 18.113000869750977,
    "model_name": "resnet50",
    "recv_time": 27929368,
    "tag": "906",
    "total_cost_by_ms": 26.834999084472656,
    "wait_cost": 3.9129981994628906
}
