{
    "child_model_execute_cost_by_ms": [
        15.156999588012695,
        8.718000411987305
    ],
    "child_model_run_time": [
        [
            25897974,
            25913131
        ],
        [
            25913169,
            25921887
        ]
    ],
    "execute_cost": 23.875,
    "finish_time": 25921895,
    "limit_cost_by_ms": 18.998332977294922,
    "model_name": "resnet50",
    "recv_time": 25857848,
    "tag": "780",
    "total_cost_by_ms": 64.0469970703125,
    "wait_cost": 40.1719970703125
}
