{
    "child_model_execute_cost_by_ms": [
        15.319000244140625,
        9.277000427246094
    ],
    "child_model_run_time": [
        [
            21578186,
            21593505
        ],
        [
            21593604,
            21602881
        ]
    ],
    "execute_cost": 24.59600067138672,
    "finish_time": 21602890,
    "limit_cost_by_ms": 18.98699951171875,
    "model_name": "resnet50",
    "recv_time": 21541197,
    "tag": "655",
    "total_cost_by_ms": 61.69300079345703,
    "wait_cost": 37.09700012207031
}
