{
    "child_model_execute_cost_by_ms": [
        15.434000015258789,
        9.678999900817871
    ],
    "child_model_run_time": [
        [
            36889226,
            36904660
        ],
        [
            36904751,
            36914430
        ]
    ],
    "execute_cost": 25.112998962402344,
    "finish_time": 36914436,
    "limit_cost_by_ms": 19.04133415222168,
    "model_name": "resnet50",
    "recv_time": 36889080,
    "tag": "994",
    "total_cost_by_ms": 25.356000900268555,
    "wait_cost": 0.24300193786621094
}
