{
    "child_model_execute_cost_by_ms": [
        17.39900016784668,
        15.333000183105469
    ],
    "child_model_run_time": [
        [
            32886925,
            32904324
        ],
        [
            32917183,
            32932516
        ]
    ],
    "execute_cost": 32.73200225830078,
    "finish_time": 32932526,
    "limit_cost_by_ms": 18.827667236328125,
    "model_name": "resnet50",
    "recv_time": 32886874,
    "tag": "622",
    "total_cost_by_ms": 45.652000427246094,
    "wait_cost": 12.919998168945313
}
