{
    "child_model_execute_cost_by_ms": [
        14.949999809265137,
        8.793000221252441
    ],
    "child_model_run_time": [
        [
            11905225,
            11920175
        ],
        [
            11920218,
            11929011
        ]
    ],
    "execute_cost": 23.743000030517578,
    "finish_time": 11929015,
    "limit_cost_by_ms": 18.976333618164063,
    "model_name": "resnet50",
    "recv_time": 11898891,
    "tag": "174",
    "total_cost_by_ms": 30.124000549316406,
    "wait_cost": 6.381000518798828
}
