{
    "child_model_execute_cost_by_ms": [
        18.774999618530273,
        20.57200050354004,
        20.211999893188477
    ],
    "child_model_run_time": [
        [
            39041102,
            39059877
        ],
        [
            39079818,
            39100390
        ],
        [
            39110816,
            39131028
        ]
    ],
    "execute_cost": 59.558998107910156,
    "finish_time": 39131032,
    "limit_cost_by_ms": 47.4293327331543,
    "model_name": "vgg19",
    "recv_time": 39041048,
    "tag": "880",
    "total_cost_by_ms": 89.98400115966797,
    "wait_cost": 30.425003051757813
}
