{
    "child_model_execute_cost_by_ms": [
        19.687999725341797,
        18.75200080871582,
        21.04400062561035
    ],
    "child_model_run_time": [
        [
            21346797,
            21366485
        ],
        [
            21373132,
            21391884
        ],
        [
            21391920,
            21412964
        ]
    ],
    "execute_cost": 59.48400115966797,
    "finish_time": 21412968,
    "limit_cost_by_ms": 46.569000244140625,
    "model_name": "vgg19",
    "recv_time": 21308310,
    "tag": "137",
    "total_cost_by_ms": 104.65799713134766,
    "wait_cost": 45.17399597167969
}
