{
    "child_model_execute_cost_by_ms": [
        14.673999786376953,
        8.666000366210938
    ],
    "child_model_run_time": [
        [
            20493468,
            20508142
        ],
        [
            20508182,
            20516848
        ]
    ],
    "execute_cost": 23.34000015258789,
    "finish_time": 20516856,
    "limit_cost_by_ms": 19.016332626342773,
    "model_name": "resnet50",
    "recv_time": 20483433,
    "tag": "477",
    "total_cost_by_ms": 33.42300033569336,
    "wait_cost": 10.083000183105469
}
