{
    "child_model_execute_cost_by_ms": [
        18.253999710083008,
        17.945999145507813,
        20.917999267578125
    ],
    "child_model_run_time": [
        [
            13238629,
            13256883
        ],
        [
            13267426,
            13285372
        ],
        [
            13285397,
            13306315
        ]
    ],
    "execute_cost": 57.11799621582031,
    "finish_time": 13306319,
    "limit_cost_by_ms": 47.43199920654297,
    "model_name": "vgg19",
    "recv_time": 12349459,
    "tag": "193",
    "total_cost_by_ms": 956.8599853515625,
    "wait_cost": 899.7420043945313
}
