{
    "child_model_execute_cost_by_ms": [
        18.43899917602539,
        18.591999053955078,
        21.816999435424805
    ],
    "child_model_run_time": [
        [
            27006874,
            27025313
        ],
        [
            27025351,
            27043943
        ],
        [
            27089172,
            27110989
        ]
    ],
    "execute_cost": 58.847999572753906,
    "finish_time": 27110997,
    "limit_cost_by_ms": 47.43199920654297,
    "model_name": "vgg19",
    "recv_time": 23700081,
    "tag": "651",
    "total_cost_by_ms": 3410.916015625,
    "wait_cost": 3352.068115234375
}
