{
    "child_model_execute_cost_by_ms": [
        15.376999855041504,
        9.241000175476074
    ],
    "child_model_run_time": [
        [
            15873560,
            15888937
        ],
        [
            15889037,
            15898278
        ]
    ],
    "execute_cost": 24.618000030517578,
    "finish_time": 15898286,
    "limit_cost_by_ms": 18.79866600036621,
    "model_name": "resnet50",
    "recv_time": 15864951,
    "tag": "351",
    "total_cost_by_ms": 33.334999084472656,
    "wait_cost": 8.716999053955078
}
