{
    "child_model_execute_cost_by_ms": [
        18.54599952697754,
        18.301000595092773,
        21.378999710083008
    ],
    "child_model_run_time": [
        [
            19439552,
            19458098
        ],
        [
            19466544,
            19484845
        ],
        [
            19520256,
            19541635
        ]
    ],
    "execute_cost": 58.22599792480469,
    "finish_time": 19541640,
    "limit_cost_by_ms": 47.30666732788086,
    "model_name": "vgg19",
    "recv_time": 19429946,
    "tag": "502",
    "total_cost_by_ms": 111.69400024414063,
    "wait_cost": 53.46800231933594
}
