{
    "child_model_execute_cost_by_ms": [
        14.40999984741211,
        8.765999794006348
    ],
    "child_model_run_time": [
        [
            31651497,
            31665907
        ],
        [
            31665962,
            31674728
        ]
    ],
    "execute_cost": 23.17599868774414,
    "finish_time": 31674733,
    "limit_cost_by_ms": 18.68433380126953,
    "model_name": "resnet50",
    "recv_time": 31651383,
    "tag": "965",
    "total_cost_by_ms": 23.350000381469727,
    "wait_cost": 0.17400169372558594
}
