{
    "child_model_execute_cost_by_ms": [
        18.444000244140625,
        17.268999099731445,
        19.70400047302246
    ],
    "child_model_run_time": [
        [
            16721950,
            16740394
        ],
        [
            16740423,
            16757692
        ],
        [
            16757773,
            16777477
        ]
    ],
    "execute_cost": 55.41699981689453,
    "finish_time": 16777481,
    "limit_cost_by_ms": 47.035667419433594,
    "model_name": "vgg19",
    "recv_time": 16717697,
    "tag": "391",
    "total_cost_by_ms": 59.784000396728516,
    "wait_cost": 4.367000579833984
}
