{
    "child_model_execute_cost_by_ms": [
        14.829999923706055,
        9.192000389099121
    ],
    "child_model_run_time": [
        [
            14160473,
            14175303
        ],
        [
            14175396,
            14184588
        ]
    ],
    "execute_cost": 24.02199935913086,
    "finish_time": 14184596,
    "limit_cost_by_ms": 18.126667022705078,
    "model_name": "resnet50",
    "recv_time": 14153498,
    "tag": "270",
    "total_cost_by_ms": 31.097999572753906,
    "wait_cost": 7.076000213623047
}
