{
    "child_model_execute_cost_by_ms": [
        15.489999771118164,
        8.991999626159668
    ],
    "child_model_run_time": [
        [
            25081023,
            25096513
        ],
        [
            25096611,
            25105603
        ]
    ],
    "execute_cost": 24.481998443603516,
    "finish_time": 25105611,
    "limit_cost_by_ms": 19.045333862304688,
    "model_name": "resnet50",
    "recv_time": 25078056,
    "tag": "742",
    "total_cost_by_ms": 27.55500030517578,
    "wait_cost": 3.0730018615722656
}
