{
    "child_model_execute_cost_by_ms": [
        19.770000457763672,
        18.76799964904785,
        20.6560001373291
    ],
    "child_model_run_time": [
        [
            30822298,
            30842068
        ],
        [
            30875222,
            30893990
        ],
        [
            30894030,
            30914686
        ]
    ],
    "execute_cost": 59.194000244140625,
    "finish_time": 30914690,
    "limit_cost_by_ms": 47.15700149536133,
    "model_name": "vgg19",
    "recv_time": 30822177,
    "tag": "984",
    "total_cost_by_ms": 92.51300048828125,
    "wait_cost": 33.319000244140625
}
