{
    "child_model_execute_cost_by_ms": [
        19.538999557495117,
        18.84000015258789,
        20.041000366210938
    ],
    "child_model_run_time": [
        [
            39537597,
            39557136
        ],
        [
            39573774,
            39592614
        ],
        [
            39592651,
            39612692
        ]
    ],
    "execute_cost": 58.41999816894531,
    "finish_time": 39612694,
    "limit_cost_by_ms": 46.66600036621094,
    "model_name": "vgg19",
    "recv_time": 39507057,
    "tag": "895",
    "total_cost_by_ms": 105.63700103759766,
    "wait_cost": 47.217002868652344
}
