{
    "child_model_execute_cost_by_ms": [
        14.649999618530273,
        8.685999870300293
    ],
    "child_model_run_time": [
        [
            18962885,
            18977535
        ],
        [
            18977561,
            18986247
        ]
    ],
    "execute_cost": 23.33599853515625,
    "finish_time": 18986251,
    "limit_cost_by_ms": 19.139333724975586,
    "model_name": "resnet50",
    "recv_time": 18962797,
    "tag": "533",
    "total_cost_by_ms": 23.45400047302246,
    "wait_cost": 0.11800193786621094
}
