{
    "child_model_execute_cost_by_ms": [
        18.059999465942383,
        17.868000030517578,
        22.115999221801758
    ],
    "child_model_run_time": [
        [
            27847360,
            27865420
        ],
        [
            27875760,
            27893628
        ],
        [
            27902149,
            27924265
        ]
    ],
    "execute_cost": 58.04399871826172,
    "finish_time": 27924269,
    "limit_cost_by_ms": 47.64500045776367,
    "model_name": "vgg19",
    "recv_time": 27847204,
    "tag": "958",
    "total_cost_by_ms": 77.06500244140625,
    "wait_cost": 19.02100372314453
}
