{
    "child_model_execute_cost_by_ms": [
        14.869999885559082,
        9.10200023651123
    ],
    "child_model_run_time": [
        [
            12207314,
            12222184
        ],
        [
            12222278,
            12231380
        ]
    ],
    "execute_cost": 23.972000122070313,
    "finish_time": 12231388,
    "limit_cost_by_ms": 18.889999389648438,
    "model_name": "resnet50",
    "recv_time": 12193394,
    "tag": "185",
    "total_cost_by_ms": 37.99399948120117,
    "wait_cost": 14.02199935913086
}
