{
    "child_model_execute_cost_by_ms": [
        18.356000900268555,
        16.742000579833984,
        20.259000778198242
    ],
    "child_model_run_time": [
        [
            11348696,
            11367052
        ],
        [
            11367140,
            11383882
        ],
        [
            11383965,
            11404224
        ]
    ],
    "execute_cost": 55.35700225830078,
    "finish_time": 11404229,
    "limit_cost_by_ms": 47.259334564208984,
    "model_name": "vgg19",
    "recv_time": 11348629,
    "tag": "160",
    "total_cost_by_ms": 55.599998474121094,
    "wait_cost": 0.2429962158203125
}
