{
    "child_model_execute_cost_by_ms": [
        18.325000762939453,
        18.32200050354004,
        21.23699951171875
    ],
    "child_model_run_time": [
        [
            21793029,
            21811354
        ],
        [
            21821652,
            21839974
        ],
        [
            21864819,
            21886056
        ]
    ],
    "execute_cost": 57.884002685546875,
    "finish_time": 21886061,
    "limit_cost_by_ms": 47.31800079345703,
    "model_name": "vgg19",
    "recv_time": 21792865,
    "tag": "604",
    "total_cost_by_ms": 93.19599914550781,
    "wait_cost": 35.31199645996094
}
