{
    "child_model_execute_cost_by_ms": [
        18.61400032043457,
        18.881000518798828,
        20.569000244140625
    ],
    "child_model_run_time": [
        [
            15952602,
            15971216
        ],
        [
            15995775,
            16014656
        ],
        [
            16014744,
            16035313
        ]
    ],
    "execute_cost": 58.064002990722656,
    "finish_time": 16035318,
    "limit_cost_by_ms": 47.14699935913086,
    "model_name": "vgg19",
    "recv_time": 15952410,
    "tag": "295",
    "total_cost_by_ms": 82.90799713134766,
    "wait_cost": 24.843994140625
}
