{
    "child_model_execute_cost_by_ms": [
        19.202999114990234,
        17.233999252319336,
        19.91699981689453
    ],
    "child_model_run_time": [
        [
            31760576,
            31779779
        ],
        [
            31779871,
            31797105
        ],
        [
            31797200,
            31817117
        ]
    ],
    "execute_cost": 56.35399627685547,
    "finish_time": 31817124,
    "limit_cost_by_ms": 47.042999267578125,
    "model_name": "vgg19",
    "recv_time": 31760415,
    "tag": "959",
    "total_cost_by_ms": 56.70899963378906,
    "wait_cost": 0.35500335693359375
}
