{
    "child_model_execute_cost_by_ms": [
        14.958000183105469,
        14.927000045776367
    ],
    "child_model_run_time": [
        [
            23309565,
            23324523
        ],
        [
            23341525,
            23356452
        ]
    ],
    "execute_cost": 29.885000228881836,
    "finish_time": 23356456,
    "limit_cost_by_ms": 18.706666946411133,
    "model_name": "resnet50",
    "recv_time": 23299246,
    "tag": "221",
    "total_cost_by_ms": 57.209999084472656,
    "wait_cost": 27.32499885559082
}
