{
    "child_model_execute_cost_by_ms": [
        18.861000061035156,
        17.121000289916992,
        21.60099983215332
    ],
    "child_model_run_time": [
        [
            18625751,
            18644612
        ],
        [
            18644700,
            18661821
        ],
        [
            18699766,
            18721367
        ]
    ],
    "execute_cost": 57.58300018310547,
    "finish_time": 18721370,
    "limit_cost_by_ms": 46.569332122802734,
    "model_name": "vgg19",
    "recv_time": 18625649,
    "tag": "23",
    "total_cost_by_ms": 95.72100067138672,
    "wait_cost": 38.13800048828125
}
