{
    "child_model_execute_cost_by_ms": [
        14.916000366210938,
        14.166999816894531
    ],
    "child_model_run_time": [
        [
            24388547,
            24403463
        ],
        [
            24413917,
            24428084
        ]
    ],
    "execute_cost": 29.08300018310547,
    "finish_time": 24428089,
    "limit_cost_by_ms": 18.882667541503906,
    "model_name": "resnet50",
    "recv_time": 24376916,
    "tag": "267",
    "total_cost_by_ms": 51.17300033569336,
    "wait_cost": 22.09000015258789
}
