{
    "child_model_execute_cost_by_ms": [
        14.793000221252441,
        13.282999992370605
    ],
    "child_model_run_time": [
        [
            30925440,
            30940233
        ],
        [
            30940269,
            30953552
        ]
    ],
    "execute_cost": 28.076000213623047,
    "finish_time": 30953556,
    "limit_cost_by_ms": 18.882667541503906,
    "model_name": "resnet50",
    "recv_time": 30918242,
    "tag": "548",
    "total_cost_by_ms": 35.31399917602539,
    "wait_cost": 7.237998962402344
}
