{
    "child_model_execute_cost_by_ms": [
        14.699000358581543,
        8.810999870300293
    ],
    "child_model_run_time": [
        [
            15233911,
            15248610
        ],
        [
            15248707,
            15257518
        ]
    ],
    "execute_cost": 23.510000228881836,
    "finish_time": 15257526,
    "limit_cost_by_ms": 18.126667022705078,
    "model_name": "resnet50",
    "recv_time": 15217266,
    "tag": "316",
    "total_cost_by_ms": 40.2599983215332,
    "wait_cost": 16.749998092651367
}
