{
    "child_model_execute_cost_by_ms": [
        15.491999626159668,
        9.057000160217285
    ],
    "child_model_run_time": [
        [
            21275519,
            21291011
        ],
        [
            21291049,
            21300106
        ]
    ],
    "execute_cost": 24.548999786376953,
    "finish_time": 21300114,
    "limit_cost_by_ms": 18.928667068481445,
    "model_name": "resnet50",
    "recv_time": 21243103,
    "tag": "558",
    "total_cost_by_ms": 57.01100158691406,
    "wait_cost": 32.46200180053711
}
