{
    "child_model_execute_cost_by_ms": [
        18.966999053955078,
        18.326000213623047,
        20.743000030517578
    ],
    "child_model_run_time": [
        [
            29747485,
            29766452
        ],
        [
            29766541,
            29784867
        ],
        [
            29784878,
            29805621
        ]
    ],
    "execute_cost": 58.0359992980957,
    "finish_time": 29805624,
    "limit_cost_by_ms": 46.50899887084961,
    "model_name": "vgg19",
    "recv_time": 29747387,
    "tag": "487",
    "total_cost_by_ms": 58.23699951171875,
    "wait_cost": 0.20100021362304688
}
