{
    "child_model_execute_cost_by_ms": [
        13.730999946594238,
        8.307000160217285
    ],
    "child_model_run_time": [
        [
            12965258,
            12978989
        ],
        [
            12979005,
            12987312
        ]
    ],
    "execute_cost": 22.038000106811523,
    "finish_time": 12987317,
    "limit_cost_by_ms": 18.1473331451416,
    "model_name": "resnet50",
    "recv_time": 12952594,
    "tag": "229",
    "total_cost_by_ms": 34.722999572753906,
    "wait_cost": 12.684999465942383
}
