{
    "child_model_execute_cost_by_ms": [
        14.677000045776367,
        8.413999557495117
    ],
    "child_model_run_time": [
        [
            23853497,
            23868174
        ],
        [
            23868267,
            23876681
        ]
    ],
    "execute_cost": 23.090999603271484,
    "finish_time": 23876688,
    "limit_cost_by_ms": 18.329999923706055,
    "model_name": "resnet50",
    "recv_time": 23853336,
    "tag": "667",
    "total_cost_by_ms": 23.351999282836914,
    "wait_cost": 0.2609996795654297
}
