{
    "child_model_execute_cost_by_ms": [
        15.126999855041504,
        8.972999572753906
    ],
    "child_model_run_time": [
        [
            29282718,
            29297845
        ],
        [
            29297898,
            29306871
        ]
    ],
    "execute_cost": 24.099998474121094,
    "finish_time": 29306878,
    "limit_cost_by_ms": 18.674999237060547,
    "model_name": "resnet50",
    "recv_time": 29282594,
    "tag": "873",
    "total_cost_by_ms": 24.284000396728516,
    "wait_cost": 0.18400192260742188
}
