{
    "child_model_execute_cost_by_ms": [
        14.972000122070313,
        8.855999946594238
    ],
    "child_model_run_time": [
        [
            28368261,
            28383233
        ],
        [
            28383326,
            28392182
        ]
    ],
    "execute_cost": 23.827999114990234,
    "finish_time": 28392188,
    "limit_cost_by_ms": 18.1473331451416,
    "model_name": "resnet50",
    "recv_time": 28368114,
    "tag": "877",
    "total_cost_by_ms": 24.073999404907227,
    "wait_cost": 0.2460002899169922
}
