{
    "child_model_execute_cost_by_ms": [
        14.6850004196167,
        8.777999877929688
    ],
    "child_model_run_time": [
        [
            20020145,
            20034830
        ],
        [
            20034918,
            20043696
        ]
    ],
    "execute_cost": 23.463001251220703,
    "finish_time": 20043704,
    "limit_cost_by_ms": 18.838666915893555,
    "model_name": "resnet50",
    "recv_time": 20003078,
    "tag": "590",
    "total_cost_by_ms": 40.625999450683594,
    "wait_cost": 17.16299819946289
}
