{
    "child_model_execute_cost_by_ms": [
        14.093999862670898,
        8.822999954223633
    ],
    "child_model_run_time": [
        [
            13231327,
            13245421
        ],
        [
            13253960,
            13262783
        ]
    ],
    "execute_cost": 22.91699981689453,
    "finish_time": 13262787,
    "limit_cost_by_ms": 18.818666458129883,
    "model_name": "resnet50",
    "recv_time": 13206583,
    "tag": "225",
    "total_cost_by_ms": 56.20399856567383,
    "wait_cost": 33.2869987487793
}
