{
    "child_model_execute_cost_by_ms": [
        18.035999298095703,
        18.538000106811523,
        21.5310001373291
    ],
    "child_model_run_time": [
        [
            30295356,
            30313392
        ],
        [
            30337990,
            30356528
        ],
        [
            30375917,
            30397448
        ]
    ],
    "execute_cost": 58.10499572753906,
    "finish_time": 30397452,
    "limit_cost_by_ms": 47.025333404541016,
    "model_name": "vgg19",
    "recv_time": 30285429,
    "tag": "907",
    "total_cost_by_ms": 112.02300262451172,
    "wait_cost": 53.918006896972656
}
