{
    "child_model_execute_cost_by_ms": [
        17.17799949645996,
        15.960000038146973,
        19.097000122070313
    ],
    "child_model_run_time": [
        [
            8355461,
            8372639
        ],
        [
            8372679,
            8388639
        ],
        [
            8410287,
            8429384
        ]
    ],
    "execute_cost": 52.23500061035156,
    "finish_time": 8429390,
    "limit_cost_by_ms": 44.548667907714844,
    "model_name": "vgg19",
    "recv_time": 8347179,
    "tag": "30",
    "total_cost_by_ms": 82.21099853515625,
    "wait_cost": 29.975997924804688
}
