{
    "child_model_execute_cost_by_ms": [
        13.255000114440918,
        8.281000137329102
    ],
    "child_model_run_time": [
        [
            8480369,
            8493624
        ],
        [
            8493711,
            8501992
        ]
    ],
    "execute_cost": 21.535999298095703,
    "finish_time": 8501996,
    "limit_cost_by_ms": 18.105667114257813,
    "model_name": "resnet50",
    "recv_time": 8465100,
    "tag": "35",
    "total_cost_by_ms": 36.895999908447266,
    "wait_cost": 15.360000610351563
}
