{
    "child_model_execute_cost_by_ms": [
        15.032999992370605,
        9.081000328063965
    ],
    "child_model_run_time": [
        [
            18743051,
            18758084
        ],
        [
            18758177,
            18767258
        ]
    ],
    "execute_cost": 24.11400032043457,
    "finish_time": 18767264,
    "limit_cost_by_ms": 18.099000930786133,
    "model_name": "resnet50",
    "recv_time": 18725605,
    "tag": "467",
    "total_cost_by_ms": 41.659000396728516,
    "wait_cost": 17.545000076293945
}
