{
    "child_model_execute_cost_by_ms": [
        15.105999946594238,
        8.541999816894531
    ],
    "child_model_run_time": [
        [
            30700517,
            30715623
        ],
        [
            30715720,
            30724262
        ]
    ],
    "execute_cost": 23.647998809814453,
    "finish_time": 30724270,
    "limit_cost_by_ms": 18.099000930786133,
    "model_name": "resnet50",
    "recv_time": 30695672,
    "tag": "963",
    "total_cost_by_ms": 28.597999572753906,
    "wait_cost": 4.950000762939453
}
