{
    "child_model_execute_cost_by_ms": [
        15.024999618530273,
        9.055999755859375
    ],
    "child_model_run_time": [
        [
            23720020,
            23735045
        ],
        [
            23735082,
            23744138
        ]
    ],
    "execute_cost": 24.08099937438965,
    "finish_time": 23744144,
    "limit_cost_by_ms": 18.889999389648438,
    "model_name": "resnet50",
    "recv_time": 23719860,
    "tag": "764",
    "total_cost_by_ms": 24.284000396728516,
    "wait_cost": 0.2030010223388672
}
