{
    "child_model_execute_cost_by_ms": [
        18.59600067138672,
        18.80299949645996,
        20.55699920654297
    ],
    "child_model_run_time": [
        [
            31685812,
            31704408
        ],
        [
            31727606,
            31746409
        ],
        [
            31755897,
            31776454
        ]
    ],
    "execute_cost": 57.95600128173828,
    "finish_time": 31776458,
    "limit_cost_by_ms": 46.810333251953125,
    "model_name": "vgg19",
    "recv_time": 31685696,
    "tag": "834",
    "total_cost_by_ms": 90.76200103759766,
    "wait_cost": 32.805999755859375
}
