{
    "child_model_execute_cost_by_ms": [
        15.343999862670898,
        8.963000297546387
    ],
    "child_model_run_time": [
        [
            8979907,
            8995251
        ],
        [
            8995294,
            9004257
        ]
    ],
    "execute_cost": 24.30699920654297,
    "finish_time": 9004266,
    "limit_cost_by_ms": 18.88599967956543,
    "model_name": "resnet50",
    "recv_time": 8970514,
    "tag": "47",
    "total_cost_by_ms": 33.75199890136719,
    "wait_cost": 9.444999694824219
}
