{
    "child_model_execute_cost_by_ms": [
        14.887999534606934,
        8.852999687194824
    ],
    "child_model_run_time": [
        [
            16899966,
            16914854
        ],
        [
            16923014,
            16931867
        ]
    ],
    "execute_cost": 23.740999221801758,
    "finish_time": 16931872,
    "limit_cost_by_ms": 18.963333129882813,
    "model_name": "resnet50",
    "recv_time": 16899905,
    "tag": "401",
    "total_cost_by_ms": 31.966999053955078,
    "wait_cost": 8.22599983215332
}
