{
    "child_model_execute_cost_by_ms": [
        15.381999969482422,
        8.791000366210938
    ],
    "child_model_run_time": [
        [
            30748779,
            30764161
        ],
        [
            30764210,
            30773001
        ]
    ],
    "execute_cost": 24.17300033569336,
    "finish_time": 30773006,
    "limit_cost_by_ms": 18.157333374023438,
    "model_name": "resnet50",
    "recv_time": 30730272,
    "tag": "965",
    "total_cost_by_ms": 42.73400115966797,
    "wait_cost": 18.56100082397461
}
