{
    "child_model_execute_cost_by_ms": [
        15.02299976348877,
        9.267000198364258
    ],
    "child_model_run_time": [
        [
            17488634,
            17503657
        ],
        [
            17503751,
            17513018
        ]
    ],
    "execute_cost": 24.290000915527344,
    "finish_time": 17513023,
    "limit_cost_by_ms": 18.930334091186523,
    "model_name": "resnet50",
    "recv_time": 17488495,
    "tag": "402",
    "total_cost_by_ms": 24.527999877929688,
    "wait_cost": 0.23799896240234375
}
