{
    "child_model_execute_cost_by_ms": [
        17.667999267578125,
        17.174999237060547,
        19.708999633789063
    ],
    "child_model_run_time": [
        [
            25639243,
            25656911
        ],
        [
            25666828,
            25684003
        ],
        [
            25684089,
            25703798
        ]
    ],
    "execute_cost": 54.551998138427734,
    "finish_time": 25703804,
    "limit_cost_by_ms": 46.900001525878906,
    "model_name": "vgg19",
    "recv_time": 25617962,
    "tag": "734",
    "total_cost_by_ms": 85.84200286865234,
    "wait_cost": 31.29000473022461
}
