{
    "child_model_execute_cost_by_ms": [
        14.869000434875488,
        9.289999961853027
    ],
    "child_model_run_time": [
        [
            26586418,
            26601287
        ],
        [
            26601409,
            26610699
        ]
    ],
    "execute_cost": 24.159000396728516,
    "finish_time": 26610709,
    "limit_cost_by_ms": 18.93400001525879,
    "model_name": "resnet50",
    "recv_time": 26571422,
    "tag": "698",
    "total_cost_by_ms": 39.2869987487793,
    "wait_cost": 15.127998352050781
}
