{
    "child_model_execute_cost_by_ms": [
        18.485000610351563,
        16.981000900268555,
        19.42099952697754
    ],
    "child_model_run_time": [
        [
            15922963,
            15941448
        ],
        [
            15941479,
            15958460
        ],
        [
            15958484,
            15977905
        ]
    ],
    "execute_cost": 54.887001037597656,
    "finish_time": 15977909,
    "limit_cost_by_ms": 46.86666488647461,
    "model_name": "vgg19",
    "recv_time": 15922860,
    "tag": "311",
    "total_cost_by_ms": 55.04899978637695,
    "wait_cost": 0.16199874877929688
}
