{
    "child_model_execute_cost_by_ms": [
        17.79800033569336,
        18.07900047302246,
        20.44099998474121
    ],
    "child_model_run_time": [
        [
            17362750,
            17380548
        ],
        [
            17415488,
            17433567
        ],
        [
            17433605,
            17454046
        ]
    ],
    "execute_cost": 56.31800079345703,
    "finish_time": 17454051,
    "limit_cost_by_ms": 46.665000915527344,
    "model_name": "vgg19",
    "recv_time": 17356261,
    "tag": "383",
    "total_cost_by_ms": 97.79000091552734,
    "wait_cost": 41.47200012207031
}
