{
    "child_model_execute_cost_by_ms": [
        17.538999557495117,
        16.68600082397461,
        20.082000732421875
    ],
    "child_model_run_time": [
        [
            19172015,
            19189554
        ],
        [
            19189652,
            19206338
        ],
        [
            19206426,
            19226508
        ]
    ],
    "execute_cost": 54.30699920654297,
    "finish_time": 19226515,
    "limit_cost_by_ms": 46.665000915527344,
    "model_name": "vgg19",
    "recv_time": 19167034,
    "tag": "457",
    "total_cost_by_ms": 59.48099899291992,
    "wait_cost": 5.173999786376953
}
