{
    "child_model_execute_cost_by_ms": [
        18.2549991607666,
        16.961000442504883,
        19.3439998626709
    ],
    "child_model_run_time": [
        [
            16877127,
            16895382
        ],
        [
            16895428,
            16912389
        ],
        [
            16912430,
            16931774
        ]
    ],
    "execute_cost": 54.55999755859375,
    "finish_time": 16931780,
    "limit_cost_by_ms": 47.12900161743164,
    "model_name": "vgg19",
    "recv_time": 16877014,
    "tag": "339",
    "total_cost_by_ms": 54.76599884033203,
    "wait_cost": 0.20600128173828125
}
