{
    "child_model_execute_cost_by_ms": [
        15.008000373840332,
        9.135000228881836
    ],
    "child_model_run_time": [
        [
            25260677,
            25275685
        ],
        [
            25275777,
            25284912
        ]
    ],
    "execute_cost": 24.143001556396484,
    "finish_time": 25284920,
    "limit_cost_by_ms": 18.836000442504883,
    "model_name": "resnet50",
    "recv_time": 25254250,
    "tag": "726",
    "total_cost_by_ms": 30.670000076293945,
    "wait_cost": 6.526998519897461
}
