{
    "child_model_execute_cost_by_ms": [
        15.414999961853027,
        9.522000312805176
    ],
    "child_model_run_time": [
        [
            36253731,
            36269146
        ],
        [
            36269233,
            36278755
        ]
    ],
    "execute_cost": 24.937000274658203,
    "finish_time": 36278759,
    "limit_cost_by_ms": 19.007667541503906,
    "model_name": "resnet50",
    "recv_time": 36253581,
    "tag": "954",
    "total_cost_by_ms": 25.17799949645996,
    "wait_cost": 0.2409992218017578
}
