{
    "child_model_execute_cost_by_ms": [
        19.07699966430664,
        17.81800079345703,
        20.375999450683594
    ],
    "child_model_run_time": [
        [
            31105465,
            31124542
        ],
        [
            31124575,
            31142393
        ],
        [
            31142417,
            31162793
        ]
    ],
    "execute_cost": 57.270999908447266,
    "finish_time": 31162798,
    "limit_cost_by_ms": 47.06666564941406,
    "model_name": "vgg19",
    "recv_time": 31105361,
    "tag": "869",
    "total_cost_by_ms": 57.4370002746582,
    "wait_cost": 0.1660003662109375
}
