{
    "child_model_execute_cost_by_ms": [
        18.96500015258789,
        19.74799919128418,
        21.09600067138672
    ],
    "child_model_run_time": [
        [
            15148900,
            15167865
        ],
        [
            15212402,
            15232150
        ],
        [
            15232240,
            15253336
        ]
    ],
    "execute_cost": 59.808998107910156,
    "finish_time": 15253341,
    "limit_cost_by_ms": 47.35933303833008,
    "model_name": "vgg19",
    "recv_time": 15148888,
    "tag": "311",
    "total_cost_by_ms": 104.4530029296875,
    "wait_cost": 44.644004821777344
}
