{
    "child_model_execute_cost_by_ms": [
        14.842000007629395,
        8.644000053405762
    ],
    "child_model_run_time": [
        [
            20257075,
            20271917
        ],
        [
            20271949,
            20280593
        ]
    ],
    "execute_cost": 23.486000061035156,
    "finish_time": 20280598,
    "limit_cost_by_ms": 18.83966636657715,
    "model_name": "resnet50",
    "recv_time": 20257061,
    "tag": "472",
    "total_cost_by_ms": 23.53700065612793,
    "wait_cost": 0.05100059509277344
}
