{
    "child_model_execute_cost_by_ms": [
        18.273000717163086,
        17.006000518798828,
        20.233999252319336
    ],
    "child_model_run_time": [
        [
            9899181,
            9917454
        ],
        [
            9917496,
            9934502
        ],
        [
            9959009,
            9979243
        ]
    ],
    "execute_cost": 55.51300048828125,
    "finish_time": 9979251,
    "limit_cost_by_ms": 46.553001403808594,
    "model_name": "vgg19",
    "recv_time": 9899007,
    "tag": "75",
    "total_cost_by_ms": 80.24400329589844,
    "wait_cost": 24.731002807617188
}
