{
    "child_model_execute_cost_by_ms": [
        14.62600040435791,
        14.61299991607666
    ],
    "child_model_run_time": [
        [
            30154620,
            30169246
        ],
        [
            30176100,
            30190713
        ]
    ],
    "execute_cost": 29.23900032043457,
    "finish_time": 30190716,
    "limit_cost_by_ms": 18.931333541870117,
    "model_name": "resnet50",
    "recv_time": 30145789,
    "tag": "515",
    "total_cost_by_ms": 44.926998138427734,
    "wait_cost": 15.687997817993164
}
