{
    "child_model_execute_cost_by_ms": [
        19.31599998474121,
        18.062999725341797,
        20.29599952697754
    ],
    "child_model_run_time": [
        [
            8572384,
            8591700
        ],
        [
            8600125,
            8618188
        ],
        [
            8618271,
            8638567
        ]
    ],
    "execute_cost": 57.67499542236328,
    "finish_time": 8638573,
    "limit_cost_by_ms": 47.42300033569336,
    "model_name": "vgg19",
    "recv_time": 8274388,
    "tag": "30",
    "total_cost_by_ms": 364.18499755859375,
    "wait_cost": 306.510009765625
}
