{
    "child_model_execute_cost_by_ms": [
        19.198999404907227,
        18.46299934387207,
        22.323999404907227
    ],
    "child_model_run_time": [
        [
            19715140,
            19734339
        ],
        [
            19777717,
            19796180
        ],
        [
            19796195,
            19818519
        ]
    ],
    "execute_cost": 59.986000061035156,
    "finish_time": 19818524,
    "limit_cost_by_ms": 47.42300033569336,
    "model_name": "vgg19",
    "recv_time": 16127203,
    "tag": "356",
    "total_cost_by_ms": 3691.321044921875,
    "wait_cost": 3631.3349609375
}
