{
    "child_model_execute_cost_by_ms": [
        14.107000350952148,
        8.98799991607666
    ],
    "child_model_run_time": [
        [
            27833325,
            27847432
        ],
        [
            27847470,
            27856458
        ]
    ],
    "execute_cost": 23.095001220703125,
    "finish_time": 27856464,
    "limit_cost_by_ms": 18.902666091918945,
    "model_name": "resnet50",
    "recv_time": 27826135,
    "tag": "843",
    "total_cost_by_ms": 30.32900047302246,
    "wait_cost": 7.233999252319336
}
